wwwml/__about__.py
wwwml/__main__.py
wwwml/tools/__init__.py
wwwml/tools/sysstat.py
wwwml-0.3.0.dist-info/METADATA
wwwml-0.3.0.dist-info/WHEEL
wwwml-0.3.0.dist-info/entry_points.txt
wwwml-0.3.0.dist-info/licenses/LICENSE
wwwml-0.3.0.dist-info/RECORD
