Metadata-Version: 2.1
Name: wwwml
Version: 0.3.0
Summary: What's wrong with my linux? A LLM based tool to diagnose linux problems.
Project-URL: homepage, https://github.com/iaalm/wwwml
Project-URL: repository, https://github.com/iaalm/wwwml
Author-email: iaalm <iaalmsimon@gmail.com>
License: MIT
License-File: LICENSE
Classifier: Development Status :: 3 - Alpha
Classifier: License :: OSI Approved :: MIT License
Classifier: Programming Language :: Python :: 3 :: Only
Classifier: Programming Language :: Python :: 3.9
Classifier: Programming Language :: Python :: 3.10
Classifier: Programming Language :: Python :: 3.11
Requires-Python: >=3.9
Requires-Dist: langchain>=0.0.271
Requires-Dist: loguru
Requires-Dist: openai>=0.27.9
